dmlab2d-1.0.0.dist-info/LICENSE.txt
dmlab2d-1.0.0.dist-info/METADATA
dmlab2d-1.0.0.dist-info/RECORD
dmlab2d-1.0.0.dist-info/WHEEL
dmlab2d/__init__.py
dmlab2d/dmlab2d_pybind.so
dmlab2d/lib/game_scripts/common/args.lua
dmlab2d/lib/game_scripts/common/class.lua
dmlab2d/lib/game_scripts/common/helpers.lua
dmlab2d/lib/game_scripts/common/image_helpers.lua
dmlab2d/lib/game_scripts/common/log.lua
dmlab2d/lib/game_scripts/common/paths.lua
dmlab2d/lib/game_scripts/common/properties.lua
dmlab2d/lib/game_scripts/common/read_settings.lua
dmlab2d/lib/game_scripts/common/set.lua
dmlab2d/lib/game_scripts/common/strings.lua
dmlab2d/lib/game_scripts/common/tables.lua
dmlab2d/lib/game_scripts/common/tile_set.lua
dmlab2d/lib/game_scripts/levels/chase_eat/images.lua
dmlab2d/lib/game_scripts/levels/chase_eat/init.lua
dmlab2d/lib/game_scripts/levels/chase_eat/level.lua
dmlab2d/lib/game_scripts/levels/chase_eat/maps.lua
dmlab2d/lib/game_scripts/levels/clean_up/avatar.lua
dmlab2d/lib/game_scripts/levels/clean_up/avatar_list.lua
dmlab2d/lib/game_scripts/levels/clean_up/images.lua
dmlab2d/lib/game_scripts/levels/clean_up/images/entities/apple.png
dmlab2d/lib/game_scripts/levels/clean_up/images/entities/banana.png
dmlab2d/lib/game_scripts/levels/clean_up/images/entities/diamond.png
dmlab2d/lib/game_scripts/levels/clean_up/images/environment/mud.png
dmlab2d/lib/game_scripts/levels/clean_up/images/environment/wall.png
dmlab2d/lib/game_scripts/levels/clean_up/images/environment/water.png
dmlab2d/lib/game_scripts/levels/clean_up/init.lua
dmlab2d/lib/game_scripts/levels/clean_up/maps.lua
dmlab2d/lib/game_scripts/levels/clean_up/simulation.lua
dmlab2d/lib/game_scripts/levels/commons_harvest/avatar.lua
dmlab2d/lib/game_scripts/levels/commons_harvest/avatar_list.lua
dmlab2d/lib/game_scripts/levels/commons_harvest/images.lua
dmlab2d/lib/game_scripts/levels/commons_harvest/init.lua
dmlab2d/lib/game_scripts/levels/commons_harvest/maps.lua
dmlab2d/lib/game_scripts/levels/commons_harvest/simulation.lua
dmlab2d/lib/game_scripts/levels/examples/level_api.lua
dmlab2d/lib/game_scripts/levels/examples/level_api_discrete_only.lua
