Metadata-Version: 2.1
Name: dmlab2d
Author: DMLab2D authors
Author-email: DeepMind Lab Team <lab@deepmind.com>
Home-page: https://github.com/deepmind/lab2d
License: Apache 2.0
Requires-Dist: dm_env
Requires-Dist: numpy
Provides-Extra: ui_renderer
Requires-Dist: pygame; extra == 'ui_renderer'
Version: 1.0.0
